{"title":"K-MOOC ─ 진행중","url":"http://www.kmooc.kr/courses?range=i","favicon":"http://www.kmooc.kr/static/images/favicon.48298a133a52.ico","elements":[{"title":"vivid social venture start-up story","contents":"<div class=\"kr01-subtext\">\n                <span class=\"kr01_professor\">\n                Lee Euiheon\n                </span>\n                <span class=\"kr01_school\">Hanyang Women’s University</span>\n                </div>\n                <div><time>2022/03/02</time>\n                \n                ~ <time>2022/06/14</time>\n                \n                </div>","retrieved":1646205138918,"image":"http://www.kmooc.kr/asset-v1:HYWoman+HYW100+2022_T1_05+type@asset+block@_%EC%98%81%EC%96%B4_K-MOOC__22_%EC%83%9D%EC%83%9D%ED%95%9C_%EC%86%8C%EC%85%9C%EB%B2%A4%EC%B2%98_%EC%B0%BD%EC%97%85_%EC%8A%A4%ED%86%A0%EB%A6%AC_%EC%8D%B8%EB%84%A4%EC%9D%BC.jpg"},{"title":"사회적 가치와 소셜벤처","contents":"<div class=\"kr01-subtext\">\n                <span class=\"kr01_professor\">\n                안지훈\n                </span>\n                <span class=\"kr01_school\">Hanyang Women’s University</span>\n                </div>\n                <div><time>2022/03/02</time>\n                \n                ~ <time>2022/06/14</time>\n                \n                </div>","retrieved":1646205138942,"image":"http://www.kmooc.kr/asset-v1:HYWoman+HYW01+2022_T1_1+type@asset+block@_CID_f_kys708oo6_CID_K-MOOC__22_%EC%8D%B8%EB%84%A4%EC%9D%BC2.jpg"},{"title":"사회적 가치와 임팩트투자","contents":"<div class=\"kr01-subtext\">\n                <span class=\"kr01_professor\">\n                주성수\n                </span>\n                <span class=\"kr01_school\">Hanyang Women’s University</span>\n                </div>\n                <div><time>2022/03/02</time>\n                \n                ~ <time>2022/06/14</time>\n                \n                </div>","retrieved":1646205138943,"image":"http://www.kmooc.kr/asset-v1:HYWoman+HYW02+2022_T1_2+type@asset+block@_CID_f_kys708ot7_CID_K-MOOC__22_%EC%8D%B8%EB%84%A4%EC%9D%BC3.jpg"},{"title":"소셜벤처 투어- 창업실무","contents":"<div class=\"kr01-subtext\">\n                <span class=\"kr01_professor\">\n                오태환\n                </span>\n                <span class=\"kr01_school\">Hanyang Women’s University</span>\n                </div>\n                <div><time>2022/03/02</time>\n                \n                ~ <time>2022/06/14</time>\n                \n                </div>","retrieved":1646205138943,"image":"http://www.kmooc.kr/asset-v1:HYWoman+HYW03+2022_T1_3+type@asset+block@_CID_f_kys708ox8_CID_K-MOOC__22_%EC%8D%B8%EB%84%A4%EC%9D%BC4.jpg"},{"title":"생생한 소셜벤처 창업 스토리","contents":"<div class=\"kr01-subtext\">\n                <span class=\"kr01_professor\">\n                이의헌\n                </span>\n                <span class=\"kr01_school\">Hanyang Women’s University</span>\n                </div>\n                <div><time>2022/03/02</time>\n                \n                ~ <time>2022/06/14</time>\n                \n                </div>","retrieved":1646205138943,"image":"http://www.kmooc.kr/asset-v1:HYWoman+HYW04+2022_T1_4+type@asset+block@_CID_f_kys708p19_CID_K-MOOC__22_%EC%8D%B8%EB%84%A4%EC%9D%BC5.jpg"},{"title":"블록체인과 정보보호","contents":"<div class=\"kr01-subtext\">\n                <span class=\"kr01_professor\">\n                유혜정 and 2 others\n                </span>\n                <span class=\"kr01_school\">Sejong Cyber University</span>\n                </div>\n                <div><time>2022/03/02</time>\n                \n                ~ <time>2022/06/13</time>\n                \n                </div>","retrieved":1646205138944,"image":"http://www.kmooc.kr/asset-v1:SJCU+SJCU03+2022_1+type@asset+block@03_%EB%B8%94%EB%A1%9D%EC%B2%B4%EC%9D%B8%EA%B3%BC-%EC%A0%95%EB%B3%B4%EB%B3%B4%ED%98%B8_2022-1_ss.jpg"},{"title":"알기 쉬운 블록체인","contents":"<div class=\"kr01-subtext\">\n                <span class=\"kr01_professor\">\n                장남수 and 3 others\n                </span>\n                <span class=\"kr01_school\">Sejong Cyber University</span>\n                </div>\n                <div><time>2022/03/02</time>\n                \n                ~ <time>2022/06/13</time>\n                \n                </div>","retrieved":1646205138947,"image":"http://www.kmooc.kr/asset-v1:SJCU+SJCU01+2022_1+type@asset+block@01_%EC%95%8C%EA%B8%B0%EC%89%AC%EC%9A%B4-%EB%B8%94%EB%A1%9D%EC%B2%B4%EC%9D%B8_2022-1_ss.jpg"},{"title":"성공적인 소셜벤처 창업을 위한 실무 개론","contents":"<div class=\"kr01-subtext\">\n                <span class=\"kr01_professor\">\n                노성여 and 5 others\n                </span>\n                <span class=\"kr01_school\">Tongmyong University</span>\n                </div>\n                <div><time>2022/03/02</time>\n                \n                ~ <time>2022/06/20</time>\n                \n                </div>","retrieved":1646205138948,"image":"http://www.kmooc.kr/asset-v1:TUk+LINC_TUMOOC0002+2022_T1+type@asset+block@%EC%84%B1%EA%B3%B5%EC%A0%81%EC%9D%B8%EC%86%8C%EC%85%9C%EB%B2%A4%EC%B2%98%EC%B0%BD%EC%97%85%EC%9D%84%EC%9C%84%ED%95%9C%EC%8B%A4%EB%AC%B4%EA%B0%9C%EB%A1%A0_%EC%8D%B8%EB%84%A4%EC%9D%BC.jpg"},{"title":"민족의 지성 다산 정약용의 삶과 철학","contents":"<div class=\"kr01-subtext\">\n                <span class=\"kr01_professor\">\n                손흥철(孫興徹)\n                </span>\n                <span class=\"kr01_school\">ANYANG UNIVERSITY</span>\n                </div>\n                <div><time>2022/03/02</time>\n                \n                ~ <time>2022/06/08</time>\n                \n                </div>","retrieved":1646205138948,"image":"http://www.kmooc.kr/asset-v1:AYUk+AYUK_DJ+2022_T1+type@asset+block@%EC%8D%B8%EB%84%A4%EC%9D%BC_%EC%A0%95%EC%95%BD%EC%9A%A9_%EC%A0%81%EC%9A%A9%EB%B3%B8_2_%EC%B6%95%EC%86%8C.jpg"},{"title":"5분 안에 톺아보는 ‘북한의 민족유산(문화재)’","contents":"<div class=\"kr01-subtext\">\n                <span class=\"kr01_professor\">\n                장용철\n                </span>\n                <span class=\"kr01_school\">ANYANG UNIVERSITY</span>\n                </div>\n                <div><time>2022/03/02</time>\n                \n                ~ <time>2022/06/08</time>\n                \n                </div>","retrieved":1646205138956,"image":"http://www.kmooc.kr/asset-v1:AYUk+AYUK_IP_0+2022_T1+type@asset+block@%EC%95%88%EC%96%91%EB%8C%80_%EB%B6%81%ED%95%9C%EC%9D%98_%EB%AF%BC%EC%A1%B1%EC%9C%A0%EC%82%B0_%EC%8D%B8%EB%84%A4%EC%9D%BC_%EC%88%98%EC%A0%95.jpg"},{"title":"현재와 과거를 잇는 한국문화사","contents":"<div class=\"kr01-subtext\">\n                <span class=\"kr01_professor\">\n                김인호\n                </span>\n                <span class=\"kr01_school\">KWANGWOON UNIVERSITY</span>\n                </div>\n                <div><time>2022/03/02</time>\n                \n                ~ <time>2022/06/22</time>\n                \n                </div>","retrieved":1646205138956,"image":"http://www.kmooc.kr/asset-v1:KWU+KWU01+2022_T1+type@asset+block@%ED%95%9C%EA%B5%AD-%EB%AC%B8%ED%99%94%EC%82%AC_2021-2_.jpg"},{"title":"4차 산업혁명, 찐 고수되기","contents":"<div class=\"kr01-subtext\">\n                <span class=\"kr01_professor\">\n                정동훈\n                </span>\n                <span class=\"kr01_school\">KWANGWOON UNIVERSITY</span>\n                </div>\n                <div><time>2022/03/02</time>\n                \n                ~ <time>2022/06/22</time>\n                \n                </div>","retrieved":1646205138956,"image":"http://www.kmooc.kr/asset-v1:KWU+KWU07+2022_T1+type@asset+block@2021_2%EC%B0%90%EA%B3%A0%EC%88%98%EB%90%98%EA%B8%B0.png"},{"title":"한국영화사로 보는 가족","contents":"<div class=\"kr01-subtext\">\n                <span class=\"kr01_professor\">\n                강성률\n                </span>\n                <span class=\"kr01_school\">KWANGWOON UNIVERSITY</span>\n                </div>\n                <div><time>2022/03/02</time>\n                \n                ~ <time>2022/06/22</time>\n                \n                </div>","retrieved":1646205138987,"image":"http://www.kmooc.kr/asset-v1:KWU+KWU_05+2022_T1+type@asset+block@%ED%95%9C%EA%B5%AD%EC%98%81%ED%99%94%EC%82%AC_2021-2_.jpg"},{"title":"플라즈마와 건강, 그리고 생활문화","contents":"<div class=\"kr01-subtext\">\n                <span class=\"kr01_professor\">\n                최은하 and 4 others\n                </span>\n                <span class=\"kr01_school\">KWANGWOON UNIVERSITY</span>\n                </div>\n                <div><time>2022/03/02</time>\n                \n                ~ <time>2022/06/21</time>\n                \n                </div>","retrieved":1646205138990,"image":"http://www.kmooc.kr/asset-v1:KWU+KWU_06+2022_T1+type@asset+block@%ED%94%8C%EB%9D%BC%EC%A6%88%EB%A7%88_2021-2_.jpg"},{"title":"수학사","contents":"<div class=\"kr01-subtext\">\n                <span class=\"kr01_professor\">\n                허민\n                </span>\n                <span class=\"kr01_school\">KWANGWOON UNIVERSITY</span>\n                </div>\n                <div><time>2022/03/02</time>\n                \n                ~ <time>2022/06/21</time>\n                \n                </div>","retrieved":1646205138993,"image":"http://www.kmooc.kr/asset-v1:KWU+KWU_02+2022_T1+type@asset+block@%EC%88%98%ED%95%99%EC%82%AC_2021-2_.jpg"},{"title":"우리 문화 속의 한자어","contents":"<div class=\"kr01-subtext\">\n                <span class=\"kr01_professor\">\n                김용재\n                </span>\n                <span class=\"kr01_school\">SUNGSHIN WOMEN'S UNIVERSITY</span>\n                </div>\n                <div><time>2022/03/02</time>\n                \n                ~ <time>2022/06/23</time>\n                \n                </div>","retrieved":1646205138995,"image":"http://www.kmooc.kr/asset-v1:SSUk+SSMOOC02K+2022_T1+type@asset+block@006.png"},{"title":"융합예술과 문화공간 기획","contents":"<div class=\"kr01-subtext\">\n                <span class=\"kr01_professor\">\n                김보름\n                </span>\n                <span class=\"kr01_school\">Sejong University</span>\n                </div>\n                <div><time>2022/03/02</time>\n                \n                ~ <time>2022/06/14</time>\n                \n                </div>","retrieved":1646205138998,"image":"http://www.kmooc.kr/asset-v1:SejonguniversityK+SJKMOOC21k+2022_06SJ21_R+type@asset+block@2022-1__%EC%8D%B8%EB%84%A4%EC%9D%BC__%EC%9C%B5%ED%95%A9%EC%98%88%EC%88%A0%EA%B3%BC_%EB%AC%B8%ED%99%94%EA%B3%B5%EA%B0%84_%EA%B8%B0%ED%9A%8D.jpg"},{"title":"웨어러블 컴퓨터 디자인","contents":"<div class=\"kr01-subtext\">\n                <span class=\"kr01_professor\">\n                김숙진 and 1 others\n                </span>\n                <span class=\"kr01_school\">Sejong University</span>\n                </div>\n                <div><time>2022/03/02</time>\n                \n                ~ <time>2022/06/14</time>\n                \n                </div>","retrieved":1646205139002,"image":"http://www.kmooc.kr/asset-v1:SejonguniversityK+SJKMOOC06k+2022_02SJ6_R+type@asset+block@2022-1__%EC%8D%B8%EB%84%A4%EC%9D%BC__%EC%9B%A8%EC%96%B4%EB%9F%AC%EB%B8%94_%EC%BB%B4%ED%93%A8%ED%84%B0_%EB%94%94%EC%9E%90%EC%9D%B8.jpg"},{"title":"모두를 위한 머신러닝","contents":"<div class=\"kr01-subtext\">\n                <span class=\"kr01_professor\">\n                공성곤\n                </span>\n                <span class=\"kr01_school\">Sejong University</span>\n                </div>\n                <div><time>2022/03/02</time>\n                \n                ~ <time>2022/06/14</time>\n                \n                </div>","retrieved":1646205139004,"image":"http://www.kmooc.kr/asset-v1:SejonguniversityK+SJKMOOC20k+2022_06SJ20_R+type@asset+block@2022-1__%EC%8D%B8%EB%84%A4%EC%9D%BC__%EB%AA%A8%EB%91%90%EB%A5%BC_%EC%9C%84%ED%95%9C_%EB%A8%B8%EC%8B%A0%EB%9F%AC%EB%8B%9D.jpg"},{"title":"일반인을 위한 물리 코딩","contents":"<div class=\"kr01-subtext\">\n                <span class=\"kr01_professor\">\n                송오영\n                </span>\n                <span class=\"kr01_school\">Sejong University</span>\n                </div>\n                <div><time>2022/03/02</time>\n                \n                ~ <time>2022/06/14</time>\n                \n                </div>","retrieved":1646205139024,"image":"http://www.kmooc.kr/asset-v1:SejonguniversityK+SJMOOC09K+2022_03SJ9_R+type@asset+block@2022-1__%EC%8D%B8%EB%84%A4%EC%9D%BC__%EC%9D%BC%EB%B0%98%EC%9D%B8%EC%9D%84_%EC%9C%84%ED%95%9C_%EB%AC%BC%EB%A6%AC_%EC%BD%94%EB%94%A9.jpg"}]}