{"title":"K-MOOC ─ 진행중","url":"http://www.kmooc.kr/courses?range=i","favicon":"http://www.kmooc.kr/static/images/favicon.48298a133a52.ico","elements":[{"title":"UX/UI 디자인 입문","contents":"<div class=\"kr01-subtext\">\n                <span class=\"kr01_professor\">\n                정의태 and 2 others\n                </span>\n                <span class=\"kr01_school\">HANYANG UNIVERSITY</span>\n                </div>\n                <div><time>2022/05/06</time>\n                \n                ~ <time>2022/07/31</time>\n                \n                </div>","link":"http://www.kmooc.kr/courses/course-v1:HYUk+HYUkBU_HYUKEMOOC2022-1k+2022_C1/about","retrieved":1651835540918,"image":"http://www.kmooc.kr/asset-v1:HYUk+HYUkBU_HYUKEMOOC2022-1k+2022_C1+type@asset+block@%ED%95%9C%EC%96%91%EB%8C%80%ED%95%99%EA%B5%90-UXUI_%EC%9E%85%EB%AC%B8%EB%B6%80%ED%84%B0_%EC%8B%AC%ED%99%94%EA%B9%8C%EC%A7%80_%EC%A0%95%EC%9D%98%ED%83%9C__%EC%A0%95%EC%9D%98%EC%B2%A0__%EC%97%B0%EB%AA%85%ED%9D%A0_-UXUI_%EB%94%94%EC%9E%90%EC%9D%B8_%EC%9E%85%EB%AC%B8_UXUI_Design_Basic_.jpg"},{"title":"연극으로 하는 창의감성교육","contents":"<div class=\"kr01-subtext\">\n                <span class=\"kr01_professor\">\n                이기호 and 1 others\n                </span>\n                <span class=\"kr01_school\">KYUNGSUNG UNIVERSITY</span>\n                </div>\n                <div><time>2022/05/04</time>\n                \n                ~ <time>2022/08/09</time>\n                \n                </div>","link":"http://www.kmooc.kr/courses/course-v1:KSUk+KSUk_14+2022_T1/about","retrieved":1651626228907,"image":"http://www.kmooc.kr/asset-v1:KSUk+KSUk_14+2022_T1+type@asset+block@%EC%B0%BD%EC%9D%98%EA%B0%90%EC%84%B1K-MOOC-%EC%8D%B8%EB%84%A4%EC%9D%BC.jpg"},{"title":"스마트폰으로 영화 만들기","contents":"<div class=\"kr01-subtext\">\n                <span class=\"kr01_professor\">\n                양영철\n                </span>\n                <span class=\"kr01_school\">KYUNGSUNG UNIVERSITY</span>\n                </div>\n                <div><time>2022/05/04</time>\n                \n                ~ <time>2022/08/09</time>\n                \n                </div>","link":"http://www.kmooc.kr/courses/course-v1:KSUk+KSUk_11+2022_T1/about","retrieved":1651626228909,"image":"http://www.kmooc.kr/asset-v1:KSUk+KSUk_11+2022_T1+type@asset+block@2022-%EC%8A%A4%EB%A7%88%ED%8A%B8%ED%8F%B0%EC%9C%BC%EB%A1%9C-%EC%98%81%ED%99%94-%EB%A7%8C%EB%93%A4%EA%B8%B0.jpg"},{"title":"시나리오란 무엇인가?","contents":"<div class=\"kr01-subtext\">\n                <span class=\"kr01_professor\">\n                강내영\n                </span>\n                <span class=\"kr01_school\">KYUNGSUNG UNIVERSITY</span>\n                </div>\n                <div><time>2022/05/04</time>\n                \n                ~ <time>2022/08/09</time>\n                \n                </div>","link":"http://www.kmooc.kr/courses/course-v1:KSUk+KSUk_15+2022_T1/about","retrieved":1651626228921,"image":"http://www.kmooc.kr/asset-v1:KSUk+KSUk_15+2022_T1+type@asset+block@%EC%8B%9C%EB%82%98%EB%A6%AC%EC%98%A4%EB%9E%80-%EB%AC%B4%EC%97%87%EC%9D%B8%EA%B0%80-K-MOOC-%EC%8D%B8%EB%84%A4%EC%9D%BC.jpg"},{"title":"연기와 오디션 테크닉","contents":"<div class=\"kr01-subtext\">\n                <span class=\"kr01_professor\">\n                이기호\n                </span>\n                <span class=\"kr01_school\">KYUNGSUNG UNIVERSITY</span>\n                </div>\n                <div><time>2022/05/04</time>\n                \n                ~ <time>2022/08/09</time>\n                \n                </div>","link":"http://www.kmooc.kr/courses/course-v1:KSUk+KSUk_10+2022_T1/about","retrieved":1651626228925,"image":"http://www.kmooc.kr/asset-v1:KSUk+KSUk_10+2022_T1+type@asset+block@2022-%EC%97%B0%EA%B8%B0%EC%99%80-%EC%98%A4%EB%94%94%EC%85%98-%ED%85%8C%ED%81%AC%EB%8B%89.jpg"},{"title":"도시 부산, 공간을 말하다","contents":"<div class=\"kr01-subtext\">\n                <span class=\"kr01_professor\">\n                김은정 and 1 others\n                </span>\n                <span class=\"kr01_school\">KYUNGSUNG UNIVERSITY</span>\n                </div>\n                <div><time>2022/05/04</time>\n                \n                ~ <time>2022/06/14</time>\n                \n                </div>","link":"http://www.kmooc.kr/courses/course-v1:KSUk+KSUk_16+2022_T1/about","retrieved":1651626228928,"image":"http://www.kmooc.kr/asset-v1:KSUk+KSUk_16+2022_T1+type@asset+block@%EB%8F%84%EC%8B%9C%EB%B6%80%EC%82%B0-K-MOOC-%EC%8D%B8%EB%84%A4%EC%9D%BC.jpg"},{"title":"현해탄과 근대 부산","contents":"<div class=\"kr01-subtext\">\n                <span class=\"kr01_professor\">\n                신승모\n                </span>\n                <span class=\"kr01_school\">KYUNGSUNG UNIVERSITY</span>\n                </div>\n                <div><time>2022/05/04</time>\n                \n                ~ <time>2022/06/14</time>\n                \n                </div>","link":"http://www.kmooc.kr/courses/course-v1:KSUk+KSUk_17+2022_T1/about","retrieved":1651626228928,"image":"http://www.kmooc.kr/asset-v1:KSUk+KSUk_17+2022_T1+type@asset+block@%ED%98%84%ED%95%B4%ED%83%84%EA%B3%BC-%EA%B7%BC%EB%8C%80%EB%B6%80%EC%82%B0-K-MOOC-%EC%8D%B8%EB%84%A4%EC%9D%BC.jpg"},{"title":"믿고 보는 부산 문화","contents":"<div class=\"kr01-subtext\">\n                <span class=\"kr01_professor\">\n                황병익\n                </span>\n                <span class=\"kr01_school\">KYUNGSUNG UNIVERSITY</span>\n                </div>\n                <div><time>2022/05/04</time>\n                \n                ~ <time>2022/06/14</time>\n                \n                </div>","link":"http://www.kmooc.kr/courses/course-v1:KSUk+KSUk_12+2022_T1/about","retrieved":1651626228934,"image":"http://www.kmooc.kr/asset-v1:KSUk+KSUk_12+2022_T1+type@asset+block@2022-%EB%AF%BF%EA%B3%A0-%EB%B3%B4%EB%8A%94-%EB%B6%80%EC%82%B0-%EB%AC%B8%ED%99%94.jpg"},{"title":"비름박 넘어 부산말","contents":"<div class=\"kr01-subtext\">\n                <span class=\"kr01_professor\">\n                정재형 and 1 others\n                </span>\n                <span class=\"kr01_school\">KYUNGSUNG UNIVERSITY</span>\n                </div>\n                <div><time>2022/05/04</time>\n                \n                ~ <time>2022/05/31</time>\n                \n                </div>","link":"http://www.kmooc.kr/courses/course-v1:KSUk+KSUk_13+2022_T1/about","retrieved":1651626228935,"image":"http://www.kmooc.kr/asset-v1:KSUk+KSUk_13+2022_T1+type@asset+block@2022-%EB%B9%84%EB%A6%84%EB%B0%95-%EB%84%98%EC%96%B4-%EB%B6%80%EC%82%B0%EB%A7%90.jpg"},{"title":"대한민국의 시작 '대한민국 임시정부'","contents":"<div class=\"kr01-subtext\">\n                <span class=\"kr01_professor\">\n                한시준 외\n                </span>\n                <span class=\"kr01_school\">The Independence Hall of Korea</span>\n                </div>\n                <div><time>2022/05/03</time>\n                \n                ~ <time>2022/07/18</time>\n                \n                </div>","link":"http://www.kmooc.kr/courses/course-v1:IHK+IHK02+2022-2/about","retrieved":1651569218028,"image":"http://www.kmooc.kr/asset-v1:IHK+IHK02+2022-2+type@asset+block@%EC%9E%84%EC%8B%9C%EC%A0%95%EB%B6%80.jpg"},{"title":"한국독립운동의 역사","contents":"<div class=\"kr01-subtext\">\n                <span class=\"kr01_professor\">\n                한철호 외\n                </span>\n                <span class=\"kr01_school\">The Independence Hall of Korea</span>\n                </div>\n                <div><time>2022/05/03</time>\n                \n                ~ <time>2022/07/18</time>\n                \n                </div>","link":"http://www.kmooc.kr/courses/course-v1:IHK+IHK01+2022-2/about","retrieved":1651569218029,"image":"http://www.kmooc.kr/asset-v1:IHK+IHK01+2022-2+type@asset+block@kmooc_img_420240.jpg"},{"title":"독립군의 요람 '신흥무관학교'","contents":"<div class=\"kr01-subtext\">\n                <span class=\"kr01_professor\">\n                이명화 외 \n                </span>\n                <span class=\"kr01_school\">The Independence Hall of Korea</span>\n                </div>\n                <div><time>2022/05/03</time>\n                \n                ~ <time>2022/07/18</time>\n                \n                </div>","link":"http://www.kmooc.kr/courses/course-v1:IHK+IHK03+2022-2/about","retrieved":1651569218029,"image":"http://www.kmooc.kr/asset-v1:IHK+IHK03+2022-2+type@asset+block@%EC%8B%A0%ED%9D%A5%EB%AC%B4%EA%B4%80%ED%95%99%EA%B5%90.jpg"},{"title":"아동상담: 놀이와 예술을 통한 어린이 마음치료 - 아동 문제의 이해와 놀이･예술 심리평가","contents":"<div class=\"kr01-subtext\">\n                <span class=\"kr01_professor\">\n                김세영 and 1 others\n                </span>\n                <span class=\"kr01_school\">Baekseok University</span>\n                </div>\n                <div><time>2022/05/03</time>\n                \n                ~ <time>2022/08/19</time>\n                \n                </div>","link":"http://www.kmooc.kr/courses/course-v1:BUK+BUK006+2022_T1_01/about","retrieved":1651641418855,"image":"http://www.kmooc.kr/asset-v1:BUK+BUK006+2022_T1_01+type@asset+block@_%EB%B0%B1%EC%84%9D%EB%8C%80_%EC%95%84%EB%8F%99%EB%AC%B8%EC%A0%9C%EC%9D%98%EC%9D%B4%ED%95%B4%EC%99%80%EB%86%80%EC%9D%B4%EC%98%88%EC%88%A0%EC%8B%AC%EB%A6%AC%ED%8F%89%EA%B0%80_%EC%8D%B8%EB%84%A4%EC%9D%BC.png"},{"title":"한국문화로 배우는 한국어","contents":"<div class=\"kr01-subtext\">\n                <span class=\"kr01_professor\">\n                노정은\n                </span>\n                <span class=\"kr01_school\">HANSUNG UNIVERSITY</span>\n                </div>\n                <div><time>2022/05/02</time>\n                \n                ~ <time>2022/08/15</time>\n                \n                </div>","link":"http://www.kmooc.kr/courses/course-v1:HansungK+HSKMOOCk03+2022_T1/about","retrieved":1651482842830,"image":"http://www.kmooc.kr/asset-v1:HansungK+HSKMOOCk03+2022_T1+type@asset+block@%EC%8D%B8%EB%84%A4%EC%9D%BC.jpg"},{"title":"태국어 문장 만들기","contents":"<div class=\"kr01-subtext\">\n                <span class=\"kr01_professor\">\n                안종량\n                </span>\n                <span class=\"kr01_school\">BUSAN UNIVERSITY OF FOREIGN STUDIES</span>\n                </div>\n                <div><time>2022/05/02</time>\n                \n                ~ <time>2022/06/20</time>\n                \n                </div>","link":"http://www.kmooc.kr/courses/course-v1:BUFSk+BUFS_ICFL03+2022_T1/about","retrieved":1651482842849,"image":"http://www.kmooc.kr/asset-v1:BUFSk+BUFS_ICFL03+2022_T1+type@asset+block@Thumbnail_%ED%83%9C%EA%B5%AD%EC%96%B4%EB%AC%B8%EC%9E%A5%EB%A7%8C%EB%93%A4%EA%B8%B0.png"},{"title":"폴란드어 ABC와 기초여행회화","contents":"<div class=\"kr01-subtext\">\n                <span class=\"kr01_professor\">\n                최성은\n                </span>\n                <span class=\"kr01_school\">HANKUK UNIVERSITY OF FOREIGN STUDIES</span>\n                </div>\n                <div><time>2022/05/02</time>\n                \n                ~ <time>2022/06/27</time>\n                \n                </div>","link":"http://www.kmooc.kr/courses/course-v1:HUFS+HUFS_09+2022_T1/about","retrieved":1651482842850,"image":"http://www.kmooc.kr/asset-v1:HUFS+HUFS_09+2022_T1+type@asset+block@%ED%8F%B4%EB%9E%80%EB%93%9C%EC%96%B4_%EC%8D%B8%EB%84%A4%EC%9D%BC.jpg"},{"title":"포르투갈어 Pre-A1","contents":"<div class=\"kr01-subtext\">\n                <span class=\"kr01_professor\">\n                임소라\n                </span>\n                <span class=\"kr01_school\">HANKUK UNIVERSITY OF FOREIGN STUDIES</span>\n                </div>\n                <div><time>2022/05/02</time>\n                \n                ~ <time>2022/06/27</time>\n                \n                </div>","link":"http://www.kmooc.kr/courses/course-v1:HUFS+HUFS_08+2022_T1/about","retrieved":1651482842850,"image":"http://www.kmooc.kr/asset-v1:HUFS+HUFS_08+2022_T1+type@asset+block@%ED%8F%AC%EB%A5%B4%ED%88%AC%EA%B0%88%EC%96%B4_%EC%8D%B8%EB%84%A4%EC%9D%BC.jpg"},{"title":"기초이란어(페르시아어)","contents":"<div class=\"kr01-subtext\">\n                <span class=\"kr01_professor\">\n                곽새라\n                </span>\n                <span class=\"kr01_school\">HANKUK UNIVERSITY OF FOREIGN STUDIES</span>\n                </div>\n                <div><time>2022/05/02</time>\n                \n                ~ <time>2022/06/27</time>\n                \n                </div>","link":"http://www.kmooc.kr/courses/course-v1:HUFS+HUFS_04+2022_T1/about","retrieved":1651482842851,"image":"http://www.kmooc.kr/asset-v1:HUFS+HUFS_04+2022_T1+type@asset+block@iran_card.jpg"},{"title":"기초 우즈베크어 생활회화","contents":"<div class=\"kr01-subtext\">\n                <span class=\"kr01_professor\">\n                이지은\n                </span>\n                <span class=\"kr01_school\">HANKUK UNIVERSITY OF FOREIGN STUDIES</span>\n                </div>\n                <div><time>2022/05/02</time>\n                \n                ~ <time>2022/06/27</time>\n                \n                </div>","link":"http://www.kmooc.kr/courses/course-v1:HUFS+HUFS_12+2022_T1/about","retrieved":1651482842855,"image":"http://www.kmooc.kr/asset-v1:HUFS+HUFS_12+2022_T1+type@asset+block@sum.jpg"},{"title":"스와힐리어 기초회화","contents":"<div class=\"kr01-subtext\">\n                <span class=\"kr01_professor\">\n                박정경\n                </span>\n                <span class=\"kr01_school\">HANKUK UNIVERSITY OF FOREIGN STUDIES</span>\n                </div>\n                <div><time>2022/05/02</time>\n                \n                ~ <time>2022/06/27</time>\n                \n                </div>","link":"http://www.kmooc.kr/courses/course-v1:HUFS+HUFS_07+2022_T1/about","retrieved":1651482842855,"image":"http://www.kmooc.kr/asset-v1:HUFS+HUFS_07+2022_T1+type@asset+block@%EC%8A%A4%EC%99%80%ED%9E%90%EB%A6%AC%EC%96%B4_%EC%8D%B8%EB%84%A4%EC%9D%BC.jpg"}]}